odufrn_downloader/ODUFRNDownloader.py
odufrn_downloader/__init__.py
odufrn_downloader/mixins/FilterMixin.py
odufrn_downloader/mixins/__init__.py
odufrn_downloader/mixins/filters/LevenshteinMixin.py
odufrn_downloader/mixins/filters/SimpleSearchMixin.py
odufrn_downloader/mixins/filters/YearsMixin.py
odufrn_downloader/mixins/filters/__init__.py
odufrn_downloader/modules/Env.py
odufrn_downloader/modules/File.py
odufrn_downloader/modules/Group.py
odufrn_downloader/modules/Package.py
odufrn_downloader/modules/Tag.py
odufrn_downloader/modules/__init__.py
tests/__init__.py
tests/test_env.py
tests/test_file.py
tests/test_group.py
tests/test_package.py
tests/test_tag.py
tests/utils.py
odufrn_downloader-1.2.0.dist-info/LICENSE
odufrn_downloader-1.2.0.dist-info/METADATA
odufrn_downloader-1.2.0.dist-info/WHEEL
odufrn_downloader-1.2.0.dist-info/top_level.txt
odufrn_downloader-1.2.0.dist-info/RECORD
