Metadata-Version: 2.1
Name: odufrn-downloader
Version: 1.2.0
Summary: Open Data UFRN Downloader
Home-page: https://github.com/odufrn/odufrn-downloader
Author: Open Data UFRN
Author-email: alvarofepipa@gmail.com
License: UNKNOWN
Platform: UNKNOWN
Classifier: Programming Language :: Python :: 3
Classifier: License :: OSI Approved :: MIT License
Classifier: Operating System :: OS Independent
Requires-Dist: requests
